ckb_toolkit/__init__.py
ckb_toolkit/version.py
ckb_toolkit/address/__init__.py
ckb_toolkit/address/address.py
ckb_toolkit/address/segwit_addr.py
ckb_toolkit/core/__init__.py
ckb_toolkit/core/block.py
ckb_toolkit/core/cbmt.py
ckb_toolkit/core/hash.py
ckb_toolkit/core/header.py
ckb_toolkit/core/hex_coder.py
ckb_toolkit/core/molecule.py
ckb_toolkit/core/rpc.py
ckb_toolkit/core/signer.py
ckb_toolkit/core/test_block.py
ckb_toolkit/core/test_cbmt.py
ckb_toolkit/core/test_header.py
ckb_toolkit/core/test_transaction.py
ckb_toolkit/core/transaction.py
ckb_toolkit/core/types.py
ckb_toolkit/core/uncle_block.py
ckb_toolkit/core/witness_args.py
ckb_toolkit-0.1.1.dist-info/LICENSE
ckb_toolkit-0.1.1.dist-info/METADATA
ckb_toolkit-0.1.1.dist-info/WHEEL
ckb_toolkit-0.1.1.dist-info/top_level.txt
ckb_toolkit-0.1.1.dist-info/RECORD
