Metadata-Version: 2.1
Name: ckb-toolkit
Version: 0.1.1
Summary: Nervos CKB Toolkit
Home-page: https://github.com/duanyytop/ckb-python-toolkit
Author: dylan
Author-email: dylan@nervina.io
License: MIT
Platform: UNKNOWN
Classifier: Development Status :: 2 - Pre-Alpha
Classifier: Environment :: Console
Requires-Dist: jsonrpcclient[requests]
Requires-Dist: typing-extensions
Requires-Dist: coincurve
